faust_streaming_rocksdb.libs/librocksdb-8d4e676a.so.6.14.6
faust_streaming_rocksdb.libs/libsnappy-ddb1bad0.so.1.1.4
faust_streaming_rocksdb.libs/liblz4-af1653fb.so.1.8.3
faust_streaming_rocksdb.libs/libbz2-a273e504.so.1.0.6
faust_streaming_rocksdb-0.9.3.dist-info/LICENSE
faust_streaming_rocksdb-0.9.3.dist-info/top_level.txt
faust_streaming_rocksdb-0.9.3.dist-info/WHEEL
faust_streaming_rocksdb-0.9.3.dist-info/METADATA
faust_streaming_rocksdb-0.9.3.dist-info/RECORD
rocksdb/_rocksdb.cpp
rocksdb/errors.py
rocksdb/merge_operator.pxd
rocksdb/statistics.pxd
rocksdb/merge_operators.py
rocksdb/snapshot.pxd
rocksdb/logger.pxd
rocksdb/backup.pxd
rocksdb/table_factory.pxd
rocksdb/table_properties.pxd
rocksdb/_rocksdb.cpython-38-x86_64-linux-gnu.so
rocksdb/iterator.pxd
rocksdb/universal_compaction.pxd
rocksdb/compaction_filter.pxd
rocksdb/db.pxd
rocksdb/std_memory.pxd
rocksdb/__init__.py
rocksdb/stackable_db.pxd
rocksdb/comparator.pxd
rocksdb/status.pxd
rocksdb/cache.pxd
rocksdb/concurrent_task_limiter.pxd
rocksdb/interfaces.py
rocksdb/types.pxd
rocksdb/checkpoint.pxd
rocksdb/env.pxd
rocksdb/options.pxd
rocksdb/filter_policy.pxd
rocksdb/memtablerep.pxd
rocksdb/slice_transform.pxd
rocksdb/transaction_db.pxd
rocksdb/_rocksdb.pyx
rocksdb/advanced_options.pxd
rocksdb/slice_.pxd
rocksdb/cpp/filter_policy_wrapper.hpp
rocksdb/cpp/utils.hpp
rocksdb/cpp/memtable_factories.hpp
rocksdb/cpp/write_batch_iter_helper.hpp
rocksdb/cpp/slice_transform_wrapper.hpp
rocksdb/cpp/comparator_wrapper.hpp
rocksdb/cpp/merge_operator_wrapper.hpp
rocksdb/tests/test_transaction_db.py
rocksdb/tests/test_options.py
rocksdb/tests/__init__.py
rocksdb/tests/test_memtable.py
rocksdb/tests/test_transactiondb_options.py
rocksdb/tests/test_db.py
