Metadata-Version: 2.1
Name: faust-streaming-rocksdb
Version: 0.9.3
Summary: Python bindings for RocksDB, primarily for use with Faust
Home-page: https://github.com/faust-streaming/python-rocksdb
Author: William Barnhart
Author-email: williambbarnhart@gmail.com
License: BSD License
Project-URL: Bug Reports, https://github.com/faust-streaming/python-rocksdb/issues
Project-URL: Repository, https://github.com/faust-streaming/python-rocksdb
Keywords: rocksdb
Classifier: Intended Audience :: Developers
Classifier: Natural Language :: English
Classifier: License :: OSI Approved :: BSD License
Classifier: Programming Language :: Cython
Classifier: Programming Language :: Python
Classifier: Programming Language :: Python :: 3 :: Only
Classifier: Programming Language :: Python :: 3.6
Classifier: Programming Language :: Python :: 3.7
Classifier: Programming Language :: Python :: 3.8
Classifier: Programming Language :: Python :: 3.9
Classifier: Programming Language :: Python :: 3.10
Classifier: Programming Language :: Python :: 3.11
Classifier: Programming Language :: Python :: 3.12
Classifier: Programming Language :: Python :: Implementation :: CPython
Classifier: Operating System :: POSIX
Classifier: Operating System :: POSIX :: Linux
Classifier: Operating System :: MacOS :: MacOS X
Classifier: Topic :: Database
Classifier: Development Status :: 7 - Inactive
Provides-Extra: doc
Provides-Extra: test
License-File: LICENSE
